{
	"archive" : {},
	"artifacts" : 
	[
		{
			"path" : "sefile/libSEfile.a"
		}
	],
	"backtrace" : 1,
	"backtraceGraph" : 
	{
		"commands" : 
		[
			"add_library",
			"include_directories"
		],
		"files" : 
		[
			"sefile/CMakeLists.txt",
			"CMakeLists.txt"
		],
		"nodes" : 
		[
			{
				"file" : 0
			},
			{
				"command" : 0,
				"file" : 0,
				"line" : 21,
				"parent" : 0
			},
			{
				"file" : 1
			},
			{
				"command" : 1,
				"file" : 1,
				"line" : 43,
				"parent" : 2
			}
		]
	},
	"compileGroups" : 
	[
		{
			"compileCommandFragments" : 
			[
				{
					"fragment" : " -fPIC -g -std=gnu++14 -fdiagnostics-color=always"
				}
			],
			"includes" : 
			[
				{
					"backtrace" : 3,
					"path" : "/home/lorenzo/.jdks/corretto-17.0.11/include"
				},
				{
					"backtrace" : 3,
					"path" : "/home/lorenzo/.jdks/corretto-17.0.11/include/linux"
				}
			],
			"language" : "CXX",
			"languageStandard" : 
			{
				"backtraces" : 
				[
					1
				],
				"standard" : "14"
			},
			"sourceIndexes" : 
			[
				0,
				1
			]
		}
	],
	"id" : "SEfile::@3a6a358413ec9e55d435",
	"name" : "SEfile",
	"nameOnDisk" : "libSEfile.a",
	"paths" : 
	{
		"build" : "sefile",
		"source" : "sefile"
	},
	"sourceGroups" : 
	[
		{
			"name" : "Source Files",
			"sourceIndexes" : 
			[
				0,
				1
			]
		},
		{
			"name" : "Header Files",
			"sourceIndexes" : 
			[
				2,
				3,
				4,
				5
			]
		}
	],
	"sources" : 
	[
		{
			"backtrace" : 1,
			"compileGroupIndex" : 0,
			"path" : "sefile/SEcureDB.cpp",
			"sourceGroupIndex" : 0
		},
		{
			"backtrace" : 1,
			"compileGroupIndex" : 0,
			"path" : "sefile/SEfile.cpp",
			"sourceGroupIndex" : 0
		},
		{
			"backtrace" : 1,
			"path" : "sefile/environment.h",
			"sourceGroupIndex" : 1
		},
		{
			"backtrace" : 1,
			"path" : "sefile/SEcureDB.h",
			"sourceGroupIndex" : 1
		},
		{
			"backtrace" : 1,
			"path" : "sefile/SEfile.h",
			"sourceGroupIndex" : 1
		},
		{
			"backtrace" : 1,
			"path" : "sefile/SEfile_C_interface.h",
			"sourceGroupIndex" : 1
		}
	],
	"type" : "STATIC_LIBRARY"
}
